supply_chains_backend/__init__.py
supply_chains_backend-0.1.0.dist-info/METADATA
supply_chains_backend-0.1.0.dist-info/WHEEL
supply_chains_backend-0.1.0.dist-info/entry_points.txt
supply_chains_backend-0.1.0.dist-info/RECORD
