Metadata-Version: 2.4
Name: supply-chains-backend
Version: 0.1.0
Summary: Add your description here
Author-email: Thomas Pinder <tompinder@live.co.uk>
Requires-Python: >=3.12
Requires-Dist: polars>=1.26.0
